[
  {
    "generation": "O",
    "id": 0,
    "letter": "M",
    "open": true
  },
  {
    "generation": "I",
    "id": 1,
    "letter": "A",
    "open": false,
    "startDate": "2015-10-06T00:00:00.000+01:00"
  },
  {
    "generation": "I",
    "id": 2,
    "letter": "B",
    "open": false,
    "startDate": "2015-10-20T00:00:00.000+01:00"
  },
  {
    "generation": "I",
    "id": 3,
    "letter": "C",
    "open": false,
    "startDate": "2015-11-03T00:00:00.000+01:00",
    "winnerName": "Charizard",
    "winnerNum": 6
  },
  {
    "generation": "I",
    "id": 4,
    "letter": "D",
    "open": false,
    "startDate": "2015-11-17T00:00:00.000+01:00",
    "winnerName": "Dragonite",
    "winnerNum": 149
  },
  {
    "generation": "I",
    "id": 5,
    "letter": "E",
    "open": false,
    "startDate": "2015-12-01T00:00:00.000+01:00",
    "winnerName": "Electabuzz",
    "winnerNum": 125
  },
  {
    "generation": "I",
    "id": 6,
    "letter": "F",
    "open": false,
    "startDate": "2015-12-15T00:00:00.000+01:00",
    "winnerName": "Farfetch'd",
    "winnerNum": 83
  },
  {
    "generation": "I",
    "id": 7,
    "letter": "G",
    "open": false,
    "startDate": "2016-01-05T00:00:00.000+01:00",
    "winnerName": "Gengar",
    "winnerNum": 94
  },
  {
    "generation": "I",
    "id": 8,
    "letter": "H",
    "open": false,
    "startDate": "2016-01-19T00:00:00.000+01:00",
    "winnerName": "Horsea",
    "winnerNum": 116
  },
  {
    "generation": "I",
    "id": 9,
    "letter": "I",
    "open": false,
    "startDate": "2016-02-02T00:00:00.000+01:00",
    "winnerName": "Ivysaur",
    "winnerNum": 2
  },
  {
    "generation": "I",
    "id": 10,
    "letter": "J",
    "open": false,
    "startDate": "2016-02-16T00:00:00.000+01:00",
    "winnerName": "Jolteon",
    "winnerNum": 135
  },
  {
    "generation": "I",
    "id": 11,
    "letter": "K",
    "open": false,
    "startDate": "2016-03-01T00:00:00.000+02:00",
    "winnerName": "Kabutops",
    "winnerNum": 141
  },
  {
    "generation": "I",
    "id": 12,
    "letter": "L",
    "open": false,
    "startDate": "2016-03-15T00:00:00.000+02:00",
    "winnerName": "Lapras",
    "winnerNum": 131
  },
  {
    "generation": "I",
    "id": 13,
    "letter": "M",
    "open": false,
    "startDate": "2016-04-06T00:00:00.000+02:00",
    "winnerName": "Mew",
    "winnerNum": 151
  },
  {
    "generation": "I",
    "id": 14,
    "letter": "N",
    "open": false,
    "startDate": "2016-04-19T00:00:00.000+02:00",
    "winnerName": "Ninetales",
    "winnerNum": 38
  },
  {
    "generation": "I",
    "id": 15,
    "letter": "O",
    "open": false,
    "startDate": "2016-05-10T00:00:00.000+02:00",
    "winnerName": "Omastar",
    "winnerNum": 139
  },
  {
    "generation": "I",
    "id": 16,
    "letter": "P",
    "open": false,
    "startDate": "2016-05-24T00:00:00.000+02:00",
    "winnerName": "Porygon",
    "winnerNum": 137
  },
  {
    "generation": "I",
    "id": 17,
    "letter": "R",
    "open": false,
    "startDate": "2016-06-07T00:00:00.000+02:00",
    "winnerName": "Raichu",
    "winnerNum": 26
  },
  {
    "generation": "I",
    "id": 18,
    "letter": "S",
    "open": false,
    "startDate": "2016-06-21T00:00:00.000+02:00",
    "winnerName": "Scyther",
    "winnerNum": 123
  },
  {
    "generation": "I",
    "id": 19,
    "letter": "T",
    "open": false,
    "startDate": "2016-07-05T00:00:00.000+02:00",
    "winnerName": "Tangela",
    "winnerNum": 114
  },
  {
    "generation": "I",
    "id": 20,
    "letter": "V",
    "open": false,
    "startDate": "2016-07-19T00:00:00.000+02:00",
    "winnerName": "Vaporeon",
    "winnerNum": 134
  },
  {
    "generation": "I",
    "id": 21,
    "letter": "W",
    "open": false,
    "startDate": "2016-08-09T00:00:00.000+02:00",
    "winnerName": "Wartortle",
    "winnerNum": 8
  },
  {
    "generation": "I",
    "id": 22,
    "letter": "Z",
    "open": false,
    "startDate": "2016-08-23T00:00:00.000+02:00",
    "winnerName": "Zapdos",
    "winnerNum": 145
  },
  {
    "generation": "II",
    "id": 23,
    "letter": "A",
    "open": false,
    "startDate": "2016-09-05T00:00:00.000+02:00",
    "winnerName": "Ampharos",
    "winnerNum": 181
  },
  {
    "generation": "II",
    "id": 24,
    "letter": "B",
    "open": false,
    "startDate": "2016-09-19T00:00:00.000+01:00",
    "winnerName": "Blissey",
    "winnerNum": 242
  },
  {
    "generation": "II",
    "id": 25,
    "letter": "C",
    "open": false,
    "startDate": "2016-10-03T00:00:00.000+01:00",
    "winnerName": "Crobat",
    "winnerNum": 169
  },
  {
    "generation": "II",
    "id": 26,
    "letter": "D",
    "open": false,
    "startDate": "2016-10-18T00:00:00.000+01:00",
    "winnerName": "Donphan",
    "winnerNum": 232
  },
  {
    "generation": "II",
    "id": 27,
    "letter": "E",
    "open": false,
    "startDate": "2016-11-09T00:00:00.000+01:00",
    "winnerName": "Entei",
    "winnerNum": 244
  },
  {
    "generation": "II",
    "id": 28,
    "letter": "F",
    "open": false,
    "startDate": "2016-11-23T00:00:00.000+01:00",
    "winnerName": "Feraligatr",
    "winnerNum": 160
  },
  {
    "generation": "II",
    "id": 29,
    "letter": "G",
    "open": false,
    "startDate": "2016-12-07T00:00:00.000+01:00",
    "winnerName": "Gligar",
    "winnerNum": 207
  },
  {
    "generation": "II",
    "id": 30,
    "letter": "H",
    "open": false,
    "startDate": "2017-01-04T00:00:00.000+01:00",
    "winnerName": "Heracross",
    "winnerNum": 214
  },
  {
    "generation": "II",
    "id": 31,
    "letter": "I",
    "open": false,
    "startDate": "2017-01-18T00:00:00.000+01:00",
    "winnerName": "Igglybuff",
    "winnerNum": 174
  },
  {
    "generation": "II",
    "id": 32,
    "letter": "J",
    "open": false,
    "startDate": "2017-02-07T00:00:00.000+01:00",
    "winnerName": "Jumpluff",
    "winnerNum": 189
  },
  {
    "generation": "II",
    "id": 33,
    "letter": "K",
    "open": false,
    "startDate": "2017-02-21T00:00:00.000+01:00",
    "winnerName": "Kingdra",
    "winnerNum": 230
  },
  {
    "generation": "II",
    "id": 34,
    "letter": "L",
    "open": false,
    "startDate": "2017-03-07T00:00:00.000+01:00",
    "winnerName": "Larvitar",
    "winnerNum": 246
  },
  {
    "generation": "II",
    "id": 35,
    "letter": "M",
    "open": false,
    "startDate": "2017-03-28T00:00:00.000+02:00",
    "winnerName": "Misdreavus",
    "winnerNum": 200
  },
  {
    "generation": "II",
    "id": 36,
    "letter": "N",
    "open": false,
    "startDate": "2017-04-11T00:00:00.000+02:00",
    "winnerName": "Noctowl",
    "winnerNum": 164
  },
  {
    "generation": "II",
    "id": 37,
    "letter": "O",
    "open": false,
    "startDate": "2017-04-25T00:00:00.000+02:00",
    "winnerName": "Octillery",
    "winnerNum": 224
  },
  {
    "generation": "II",
    "id": 38,
    "letter": "P",
    "open": false,
    "startDate": "2017-05-09T00:00:00.000+02:00",
    "winnerName": "Politoed",
    "winnerNum": 186
  },
  {
    "generation": "II",
    "id": 39,
    "letter": "Q",
    "open": false,
    "startDate": "2017-05-23T00:00:00.000+02:00",
    "winnerName": "Quilava",
    "winnerNum": 156
  },
  {
    "generation": "II",
    "id": 40,
    "letter": "R",
    "open": false,
    "startDate": "2017-06-07T00:00:00.000+02:00",
    "winnerName": "Raikou",
    "winnerNum": 243
  },
  {
    "generation": "II",
    "id": 41,
    "letter": "S",
    "open": false,
    "startDate": "2017-06-20T00:00:00.000+02:00",
    "winnerName": "Steelix",
    "winnerNum": 208
  },
  {
    "generation": "II",
    "id": 42,
    "letter": "T",
    "open": false,
    "startDate": "2017-07-04T00:00:00.000+02:00",
    "winnerName": "Typhlosion",
    "winnerNum": 157
  },
  {
    "generation": "II",
    "id": 43,
    "letter": "U",
    "open": false,
    "startDate": "2017-07-18T00:00:00.000+02:00",
    "winnerName": "Umbreon",
    "winnerNum": 197
  },
  {
    "generation": "II",
    "id": 44,
    "letter": "W",
    "open": false,
    "startDate": "2017-08-02T00:00:00.000+02:00",
    "winnerName": "Wobbuffet",
    "winnerNum": 202
  },
  {
    "generation": "II",
    "id": 45,
    "letter": "X",
    "open": false,
    "startDate": "2017-08-15T00:00:00.000+02:00",
    "winnerName": "Xatu",
    "winnerNum": 178
  },
  {
    "generation": "II",
    "id": 46,
    "letter": "Y",
    "open": false,
    "startDate": "2017-08-29T00:00:00.000+02:00",
    "winnerName": "Yanma",
    "winnerNum": 193
  },
  {
    "generation": "III",
    "id": 47,
    "letter": "A",
    "open": false,
    "startDate": "2017-09-12T00:00:00.000+02:00",
    "winnerName": "Aggron",
    "winnerNum": 306
  },
  {
    "generation": "III",
    "id": 48,
    "letter": "B",
    "open": false,
    "startDate": "2017-09-26T00:00:00.000+02:00",
    "winnerName": "Blaziken",
    "winnerNum": 257
  },
  {
    "generation": "III",
    "id": 49,
    "letter": "C",
    "open": false,
    "startDate": "2017-10-10T00:00:00.000+02:00",
    "winnerName": "Cacturne",
    "winnerNum": 332
  },
  {
    "generation": "III",
    "id": 50,
    "letter": "D",
    "open": false,
    "startDate": "2017-10-24T00:00:00.000+01:00",
    "winnerName": "Deoxys",
    "winnerNum": 386
  },
  {
    "generation": "III",
    "id": 51,
    "letter": "E",
    "open": false,
    "startDate": "2017-11-07T00:00:00.000+01:00",
    "winnerName": "Exploud",
    "winnerNum": 295
  },
  {
    "generation": "III",
    "id": 52,
    "letter": "F",
    "open": false,
    "startDate": "2017-11-21T00:00:00.000+01:00",
    "winnerName": "Flygon",
    "winnerNum": 330
  },
  {
    "generation": "III",
    "id": 53,
    "letter": "G",
    "open": false,
    "startDate": "2017-12-05T00:00:00.000+01:00",
    "winnerName": "Grovyle",
    "winnerNum": 253
  },
  {
    "generation": "III",
    "id": 54,
    "letter": "H",
    "open": false,
    "startDate": "2017-12-19T00:00:00.000+01:00",
    "winnerName": "Hariyama",
    "winnerNum": 297
  },
  {
    "generation": "III",
    "id": 55,
    "letter": "I",
    "open": false,
    "startDate": "2018-01-09T00:00:00.000+01:00",
    "winnerName": "Illumise",
    "winnerNum": 314
  },
  {
    "generation": "III",
    "id": 56,
    "letter": "J",
    "open": false,
    "startDate": "2018-01-23T00:00:00.000+01:00",
    "winnerName": "Jirachi",
    "winnerNum": 385
  },
  {
    "generation": "III",
    "id": 57,
    "letter": "K",
    "open": false,
    "startDate": "2018-02-06T00:00:00.000+01:00",
    "winnerName": "Kyogre",
    "winnerNum": 382
  },
  {
    "generation": "III",
    "id": 58,
    "letter": "L",
    "open": false,
    "startDate": "2018-02-20T00:00:00.000+01:00",
    "winnerName": "Latios",
    "winnerNum": 381
  },
  {
    "generation": "III",
    "id": 59,
    "letter": "M",
    "open": false,
    "startDate": "2018-03-06T00:00:00.000+01:00",
    "winnerName": "Metagross",
    "winnerNum": 376
  },
  {
    "generation": "III",
    "id": 60,
    "letter": "N",
    "open": false,
    "startDate": "2018-03-20T00:00:00.000+01:00",
    "winnerName": "Nuzleaf",
    "winnerNum": 274
  },
  {
    "generation": "III",
    "id": 61,
    "letter": "P",
    "open": false,
    "startDate": "2018-04-03T00:00:00.000+02:00",
    "winnerName": "Poochyena",
    "winnerNum": 261
  },
  {
    "generation": "III",
    "id": 62,
    "letter": "R",
    "open": false,
    "startDate": "2018-04-17T00:00:00.000+02:00",
    "winnerName": "Rayquaza",
    "winnerNum": 384
  },
  {
    "generation": "III",
    "id": 63,
    "letter": "S",
    "open": false,
    "startDate": "2018-05-01T00:00:00.000+02:00",
    "winnerName": "Slaking",
    "winnerNum": 289
  },
  {
    "generation": "III",
    "id": 64,
    "letter": "T",
    "open": false,
    "startDate": "2018-05-15T00:00:00.000+02:00",
    "winnerName": "Tropius",
    "winnerNum": 357
  },
  {
    "generation": "III",
    "id": 65,
    "letter": "V",
    "open": false,
    "startDate": "2018-05-29T00:00:00.000+02:00",
    "winnerName": "Vigoroth",
    "winnerNum": 288
  },
  {
    "generation": "III",
    "id": 66,
    "letter": "W",
    "open": false,
    "startDate": "2018-06-12T00:00:00.000+02:00",
    "winnerName": "Wailord",
    "winnerNum": 321
  },
  {
    "generation": "III",
    "id": 67,
    "letter": "Z",
    "open": false,
    "startDate": "2018-06-26T00:00:00.000+02:00",
    "winnerName": "Zangoose",
    "winnerNum": 335
  },
  {
    "generation": "IV",
    "id": 68,
    "letter": "A",
    "open": false,
    "startDate": "2018-07-10T00:00:00.000+02:00",
    "winnerName": "Abomasnow",
    "winnerNum": 460
  },
  {
    "generation": "IV",
    "id": 69,
    "letter": "B",
    "open": false,
    "startDate": "2018-07-24T00:00:00.000+02:00",
    "winnerName": "Buizel",
    "winnerNum": 418
  },
  {
    "generation": "IV",
    "id": 70,
    "letter": "C",
    "open": false,
    "startDate": "2018-08-07T00:00:00.000+02:00",
    "winnerName": "Chimchar",
    "winnerNum": 390
  },
  {
    "generation": "IV",
    "id": 71,
    "letter": "D",
    "open": false,
    "startDate": "2018-08-21T00:00:00.000+02:00",
    "winnerName": "Dialga",
    "winnerNum": 483
  },
  {
    "generation": "IV",
    "id": 72,
    "letter": "E",
    "open": false,
    "startDate": "2018-09-04T00:00:00.000+02:00",
    "winnerName": "Electivire",
    "winnerNum": 466
  },
  {
    "generation": "IV",
    "id": 73,
    "letter": "F",
    "open": false,
    "startDate": "2018-09-18T00:00:00.000+02:00",
    "winnerName": "Froslass",
    "winnerNum": 478
  },
  {
    "generation": "IV",
    "id": 74,
    "letter": "G",
    "open": false,
    "startDate": "2018-10-02T00:00:00.000+02:00",
    "winnerName": "Grotle",
    "winnerNum": 388
  },
  {
    "generation": "IV",
    "id": 75,
    "letter": "H",
    "open": false,
    "startDate": "2018-10-16T00:00:00.000+02:00",
    "winnerName": "Heatran",
    "winnerNum": 485
  },
  {
    "generation": "IV",
    "id": 76,
    "letter": "I",
    "open": false,
    "startDate": "2018-10-30T00:00:00.000+01:00",
    "winnerName": "Infernape",
    "winnerNum": 392
  },
  {
    "generation": "IV",
    "id": 77,
    "letter": "K",
    "open": false,
    "startDate": "2018-11-13T00:00:00.000+01:00",
    "winnerName": "Kricketune",
    "winnerNum": 402
  },
  {
    "generation": "IV",
    "id": 78,
    "letter": "L",
    "open": false,
    "startDate": "2018-11-27T00:00:00.000+01:00",
    "winnerName": "Luxray",
    "winnerNum": 405
  },
  {
    "generation": "IV",
    "id": 79,
    "letter": "M",
    "open": false,
    "startDate": "2018-12-11T00:00:00.000+01:00",
    "winnerName": "Munchlax",
    "winnerNum": 446
  },
  {
    "generation": "IV",
    "id": 80,
    "letter": "P",
    "open": false,
    "startDate": "2018-12-25T00:00:00.000+01:00",
    "winnerName": "Palkia",
    "winnerNum": 484
  },
  {
    "generation": "IV",
    "id": 81,
    "letter": "R",
    "open": false,
    "startDate": "2019-01-08T00:00:00.000+01:00",
    "winnerName": "Riolu",
    "winnerNum": 447
  },
  {
    "generation": "IV",
    "id": 82,
    "letter": "S",
    "open": false,
    "startDate": "2019-01-22T00:00:00.000+01:00",
    "winnerName": "Snover",
    "winnerNum": 459
  },
  {
    "generation": "IV",
    "id": 83,
    "letter": "T",
    "open": false,
    "startDate": "2019-02-05T00:00:00.000+01:00",
    "winnerName": "Torterra",
    "winnerNum": 389
  },
  {
    "generation": "IV",
    "id": 84,
    "letter": "U",
    "open": false,
    "startDate": "2019-02-19T00:00:00.000+01:00",
    "winnerName": "Uxie",
    "winnerNum": 480
  },
  {
    "generation": "IV",
    "id": 85,
    "letter": "V",
    "open": false,
    "startDate": "2019-03-05T00:00:00.000+01:00",
    "winnerName": "Vespiquen",
    "winnerNum": 416
  },
  {
    "generation": "IV",
    "id": 86,
    "letter": "W",
    "open": false,
    "startDate": "2019-03-19T00:00:00.000+01:00",
    "winnerName": "Weavile",
    "winnerNum": 461
  },
  {
    "generation": "IV",
    "id": 87,
    "letter": "Y",
    "open": false,
    "startDate": "2019-04-02T00:00:00.000+02:00",
    "winnerName": "Yanmega",
    "winnerNum": 469
  },
  {
    "generation": "V",
    "id": 88,
    "letter": "A",
    "open": false,
    "startDate": "2019-04-16T00:00:00.000+02:00",
    "winnerName": "Archeops",
    "winnerNum": 567
  },
  {
    "generation": "V",
    "id": 89,
    "letter": "B",
    "open": false,
    "startDate": "2019-04-30T00:00:00.000+02:00",
    "winnerName": "Beartic",
    "winnerNum": 614
  },
  {
    "generation": "V",
    "id": 90,
    "letter": "C",
    "open": false,
    "startDate": "2019-05-14T00:00:00.000+02:00",
    "winnerName": "Carracosta",
    "winnerNum": 565
  },
  {
    "generation": "V",
    "id": 91,
    "letter": "D",
    "open": false,
    "startDate": "2019-05-28T00:00:00.000+02:00",
    "winnerName": "Ducklett",
    "winnerNum": 580
  },
  {
    "generation": "V",
    "id": 92,
    "letter": "E",
    "open": false,
    "startDate": "2019-06-11T00:00:00.000+02:00",
    "winnerName": "Emolga",
    "winnerNum": 587
  },
  {
    "generation": "V",
    "id": 93,
    "letter": "F",
    "open": false,
    "startDate": "2019-06-25T00:00:00.000+02:00",
    "winnerName": "Fraxure",
    "winnerNum": 611
  },
  {
    "generation": "V",
    "id": 94,
    "letter": "G",
    "open": false,
    "startDate": "2019-07-09T00:00:00.000+02:00",
    "winnerName": "Gigalith",
    "winnerNum": 526
  },
  {
    "generation": "V",
    "id": 95,
    "letter": "H",
    "open": false,
    "startDate": "2019-07-23T00:00:00.000+02:00",
    "winnerName": "Hydreigon",
    "winnerNum": 635
  },
  {
    "generation": "V",
    "id": 96,
    "letter": "J",
    "open": false,
    "startDate": "2019-08-06T00:00:00.000+02:00",
    "winnerName": "Joltik",
    "winnerNum": 595
  },
  {
    "generation": "V",
    "id": 97,
    "letter": "K",
    "open": false,
    "startDate": "2019-08-20T00:00:00.000+02:00",
    "winnerName": "Krokorok",
    "winnerNum": 552
  },
  {
    "generation": "V",
    "id": 98,
    "letter": "L",
    "open": false,
    "startDate": "2019-09-03T00:00:00.000+02:00",
    "winnerName": "Lillipup",
    "winnerNum": 506
  },
  {
    "generation": "V",
    "id": 99,
    "letter": "M",
    "open": false,
    "startDate": "2019-09-17T00:00:00.000+02:00",
    "winnerName": "Mienfoo",
    "winnerNum": 619
  },
  {
    "generation": "V",
    "id": 100,
    "letter": "O",
    "open": false,
    "startDate": "2019-10-01T00:00:00.000+02:00",
    "winnerName": "Oshawott",
    "winnerNum": 501
  },
  {
    "generation": "V",
    "id": 101,
    "letter": "P",
    "open": false,
    "startDate": "2019-10-15T00:00:00.000+02:00",
    "winnerName": "Pidove",
    "winnerNum": 519
  },
  {
    "generation": "V",
    "id": 102,
    "letter": "R",
    "open": false,
    "startDate": "2019-10-29T00:00:00.000+01:00",
    "winnerName": "Reshiram",
    "winnerNum": 643
  },
  {
    "generation": "V",
    "id": 103,
    "letter": "S",
    "open": false,
    "startDate": "2019-11-12T00:00:00.000+01:00",
    "winnerName": "Simisage",
    "winnerNum": 512
  },
  {
    "generation": "V",
    "id": 104,
    "letter": "T",
    "open": false,
    "startDate": "2019-11-26T00:00:00.000+01:00",
    "winnerName": "Timburr",
    "winnerNum": 532
  },
  {
    "generation": "V",
    "id": 105,
    "letter": "U",
    "open": false,
    "startDate": "2019-12-10T00:00:00.000+01:00",
    "winnerName": "Unfezant",
    "winnerNum": 521
  },
  {
    "generation": "V",
    "id": 106,
    "letter": "V",
    "open": false,
    "startDate": "2020-01-07T00:00:00.000+01:00",
    "winnerName": "Victini",
    "winnerNum": 494
  },
  {
    "generation": "V",
    "id": 107,
    "letter": "W",
    "open": false,
    "startDate": "2020-01-21T00:00:00.000+01:00",
    "winnerName": "Watchog",
    "winnerNum": 505
  },
  {
    "generation": "V",
    "id": 108,
    "letter": "Y",
    "open": false,
    "startDate": "2020-02-04T00:00:00.000+01:00",
    "winnerName": "Yamask",
    "winnerNum": 562
  },
  {
    "generation": "V",
    "id": 109,
    "letter": "Z",
    "open": false,
    "startDate": "2020-02-18T00:00:00.000+01:00",
    "winnerName": "Zekrom",
    "winnerNum": 644
  },
  {
    "generation": "VI",
    "id": 110,
    "letter": "A",
    "open": false,
    "startDate": "2020-03-03T00:00:00.000+01:00",
    "winnerName": "Aurorus",
    "winnerNum": 699
  },
  {
    "generation": "VI",
    "id": 111,
    "letter": "B",
    "open": false,
    "startDate": "2020-03-17T00:00:00.000+01:00",
    "winnerName": "Braixen",
    "winnerNum": 654
  },
  {
    "generation": "VI",
    "id": 112,
    "letter": "C",
    "open": false,
    "startDate": "2020-03-31T00:00:00.000+02:00",
    "winnerName": "Chespin",
    "winnerNum": 650
  },
  {
    "generation": "VI",
    "id": 113,
    "letter": "D",
    "open": false,
    "startDate": "2020-04-14T00:00:00.000+02:00",
    "winnerName": "Delphox",
    "winnerNum": 655
  },
  {
    "generation": "VI",
    "id": 114,
    "letter": "E",
    "open": false,
    "startDate": "2020-04-28T00:00:00.000+02:00",
    "winnerName": "Espurr",
    "winnerNum": 677
  },
  {
    "generation": "VI",
    "id": 115,
    "letter": "F",
    "open": false,
    "startDate": "2020-05-12T00:00:00.000+02:00",
    "winnerName": "Fletchinder",
    "winnerNum": 662
  },
  {
    "generation": "VI",
    "id": 116,
    "letter": "G",
    "open": false,
    "startDate": "2020-05-26T00:00:00.000+02:00",
    "winnerName": "Gogoat",
    "winnerNum": 673
  },
  {
    "generation": "VI",
    "id": 117,
    "letter": "H",
    "open": false,
    "startDate": "2020-06-09T00:00:00.000+02:00",
    "winnerName": "Hawlucha",
    "winnerNum": 701
  },
  {
    "generation": "VI",
    "id": 118,
    "letter": "I",
    "open": false,
    "startDate": "2020-06-23T00:00:00.000+02:00",
    "winnerName": "Inkay",
    "winnerNum": 686
  },
  {
    "generation": "VI",
    "id": 119,
    "letter": "K",
    "open": false,
    "startDate": "2020-07-07T00:00:00.000+02:00",
    "winnerName": "Klefki",
    "winnerNum": 707
  },
  {
    "generation": "VI",
    "id": 120,
    "letter": "L",
    "open": false,
    "startDate": "2020-07-21T00:00:00.000+02:00",
    "winnerName": "Litleo",
    "winnerNum": 667
  },
  {
    "generation": "VI",
    "id": 121,
    "letter": "M",
    "open": false,
    "startDate": "2020-08-04T00:00:00.000+02:00",
    "winnerName": "Meowstic",
    "winnerNum": 678
  },
  {
    "generation": "VI",
    "id": 122,
    "letter": "N",
    "open": false,
    "startDate": "2020-08-18T00:00:00.000+02:00",
    "winnerName": "Noivern",
    "winnerNum": 715
  },
  {
    "generation": "VI",
    "id": 123,
    "letter": "P",
    "open": false,
    "startDate": "2020-09-01T00:00:00.000+02:00",
    "winnerName": "Pancham",
    "winnerNum": 674
  },
  {
    "generation": "VI",
    "id": 124,
    "letter": "Q",
    "open": false,
    "startDate": "2020-09-15T00:00:00.000+02:00",
    "winnerName": "Quilladin",
    "winnerNum": 651
  },
  {
    "generation": "VI",
    "id": 125,
    "letter": "S",
    "open": false,
    "startDate": "2020-09-29T00:00:00.000+02:00",
    "winnerName": "Skiddo",
    "winnerNum": 672
  },
  {
    "generation": "VI",
    "id": 126,
    "letter": "T",
    "open": false,
    "startDate": "2020-10-13T00:00:00.000+02:00",
    "winnerName": "Talonflame",
    "winnerNum": 663
  },
  {
    "generation": "VI",
    "id": 127,
    "letter": "V",
    "open": false,
    "startDate": "2020-10-27T00:00:00.000+01:00",
    "winnerName": "Volcanion",
    "winnerNum": 721
  },
  {
    "generation": "VI",
    "id": 128,
    "letter": "X",
    "open": false,
    "startDate": "2020-11-10T00:00:00.000+01:00",
    "winnerName": "Xerneas",
    "winnerNum": 716
  },
  {
    "generation": "VI",
    "id": 129,
    "letter": "Y",
    "open": false,
    "startDate": "2020-11-24T00:00:00.000+01:00",
    "winnerName": "Yveltal",
    "winnerNum": 717
  },
  {
    "generation": "VI",
    "id": 130,
    "letter": "Z",
    "open": false,
    "startDate": "2020-12-08T00:00:00.000+01:00",
    "winnerName": "Zygarde",
    "winnerNum": 718
  },
  {
    "generation": "VII",
    "id": 131,
    "letter": "A",
    "open": false,
    "startDate": "2020-12-22T00:00:00.000+01:00",
    "winnerName": "Araquanid",
    "winnerNum": 752
  },
  {
    "generation": "VII",
    "id": 132,
    "letter": "B",
    "open": false,
    "startDate": "2021-01-05T00:00:00.000+01:00",
    "winnerName": "Buzzwole",
    "winnerNum": 794
  },
  {
    "generation": "VII",
    "id": 133,
    "letter": "C",
    "open": false,
    "startDate": "2021-01-19T00:00:00.000+01:00"
  },
  {
    "generation": "VII",
    "id": 134,
    "letter": "D",
    "open": false,
    "startDate": "2021-02-02T00:00:00.000+01:00",
    "winnerName": "Drampa",
    "winnerNum": 780
  },
  {
    "generation": "VII",
    "id": 135,
    "letter": "F",
    "open": false,
    "startDate": "2021-02-16T00:00:00.000+01:00",
    "winnerName": "Fomantis",
    "winnerNum": 753
  },
  {
    "generation": "VII",
    "id": 136,
    "letter": "G",
    "open": false,
    "startDate": "2021-03-02T00:00:00.000+01:00",
    "winnerName": "Guzzlord",
    "winnerNum": 799
  },
  {
    "generation": "VII",
    "id": 137,
    "letter": "H",
    "open": false,
    "startDate": "2021-03-16T00:00:00.000+01:00",
    "winnerName": "Hakamo-o",
    "winnerNum": 783
  },
  {
    "generation": "VII",
    "id": 138,
    "letter": "I",
    "open": false,
    "startDate": "2021-03-30T00:00:00.000+02:00",
    "winnerName": "Incineroar",
    "winnerNum": 727
  },
  {
    "generation": "VII",
    "id": 139,
    "letter": "J",
    "open": false,
    "startDate": "2021-04-13T00:00:00.000+02:00",
    "winnerName": "Jangmo-o",
    "winnerNum": 782
  },
  {
    "generation": "VII",
    "id": 140,
    "letter": "K",
    "open": false,
    "startDate": "2021-04-27T00:00:00.000+02:00",
    "winnerName": "Komala",
    "winnerNum": 775
  },
  {
    "generation": "VII",
    "id": 141,
    "letter": "L",
    "open": false,
    "startDate": "2021-05-11T00:00:00.000+02:00",
    "winnerName": "Lycanroc",
    "winnerNum": 745
  },
  {
    "generation": "VII",
    "id": 142,
    "letter": "M",
    "open": false,
    "startDate": "2021-05-25T00:00:00.000+02:00",
    "winnerName": "Mudbray",
    "winnerNum": 749
  },
  {
    "generation": "VII",
    "id": 143,
    "letter": "N",
    "open": false,
    "startDate": "2021-06-08T00:00:00.000+02:00",
    "winnerName": "Nihilego",
    "winnerNum": 793
  },
  {
    "generation": "VII",
    "id": 144,
    "letter": "O",
    "open": false,
    "startDate": "2021-06-22T00:00:00.000+02:00",
    "winnerName": "Oricorio",
    "winnerNum": 741
  },
  {
    "generation": "VII",
    "id": 145,
    "letter": "P",
    "open": false,
    "startDate": "2021-07-06T00:00:00.000+02:00",
    "winnerName": "Passimian",
    "winnerNum": 766
  },
  {
    "generation": "VII",
    "id": 146,
    "letter": "R",
    "open": false,
    "startDate": "2021-07-20T00:00:00.000+02:00",
    "winnerName": "Rockruff",
    "winnerNum": 744
  },
  {
    "generation": "VII",
    "id": 147,
    "letter": "S",
    "open": false,
    "startDate": "2021-08-03T00:00:00.000+02:00",
    "winnerName": "Solgaleo",
    "winnerNum": 791
  },
  {
    "generation": "VII",
    "id": 148,
    "letter": "T",
    "open": false,
    "startDate": "2021-08-17T00:00:00.000+02:00",
    "winnerName": "Type: Null",
    "winnerNum": 772
  },
  {
    "generation": "VII",
    "id": 149,
    "letter": "V",
    "open": true,
    "startDate": "2021-08-31T00:00:00.000+02:00"
  },
  {
    "generation": "VII",
    "id": 150,
    "letter": "W",
    "open": true,
    "startDate": "2021-09-14T00:00:00.000+02:00"
  },
  {
    "generation": "VII",
    "id": 151,
    "letter": "X",
    "open": true,
    "startDate": "2021-09-28T00:00:00.000+02:00"
  },
  {
    "generation": "VII",
    "id": 152,
    "letter": "Y",
    "open": true,
    "startDate": "2021-10-12T00:00:00.000+02:00"
  },
  {
    "generation": "VII",
    "id": 153,
    "letter": "Z",
    "open": true,
    "startDate": "2021-10-26T00:00:00.000+02:00"
  },
  {
    "generation": "VIII",
    "id": 154,
    "letter": "A",
    "open": true,
    "startDate": "2021-11-09T00:00:00.000+01:00"
  },
  {
    "generation": "VIII",
    "id": 155,
    "letter": "B",
    "open": true,
    "startDate": "2021-11-23T00:00:00.000+01:00"
  },
  {
    "generation": "VIII",
    "id": 156,
    "letter": "C",
    "open": true,
    "startDate": "2021-12-07T00:00:00.000+01:00"
  },
  {
    "generation": "VIII",
    "id": 157,
    "letter": "D",
    "open": true,
    "startDate": "2021-12-21T00:00:00.000+01:00"
  },
  {
    "generation": "VIII",
    "id": 158,
    "letter": "E",
    "open": true,
    "startDate": "2022-01-04T00:00:00.000+01:00"
  },
  {
    "generation": "VIII",
    "id": 159,
    "letter": "F",
    "open": true,
    "startDate": "2022-01-18T00:00:00.000+01:00"
  },
  {
    "generation": "VIII",
    "id": 160,
    "letter": "G",
    "open": true,
    "startDate": "2022-02-01T00:00:00.000+01:00"
  },
  {
    "generation": "VIII",
    "id": 161,
    "letter": "H",
    "open": true,
    "startDate": "2022-02-15T00:00:00.000+01:00"
  },
  {
    "generation": "VIII",
    "id": 162,
    "letter": "I",
    "open": true,
    "startDate": "2022-03-01T00:00:00.000+01:00"
  },
  {
    "generation": "VIII",
    "id": 163,
    "letter": "K",
    "open": true,
    "startDate": "2022-03-15T00:00:00.000+01:00"
  },
  {
    "generation": "VIII",
    "id": 164,
    "letter": "M",
    "open": true,
    "startDate": "2022-03-29T00:00:00.000+02:00"
  },
  {
    "generation": "VIII",
    "id": 165,
    "letter": "N",
    "open": true,
    "startDate": "2022-04-12T00:00:00.000+02:00"
  },
  {
    "generation": "VIII",
    "id": 166,
    "letter": "O",
    "open": true,
    "startDate": "2022-04-26T00:00:00.000+02:00"
  },
  {
    "generation": "VIII",
    "id": 167,
    "letter": "P",
    "open": true,
    "startDate": "2022-05-10T00:00:00.000+02:00"
  },
  {
    "generation": "VIII",
    "id": 168,
    "letter": "R",
    "open": true,
    "startDate": "2022-05-24T00:00:00.000+02:00"
  },
  {
    "generation": "VIII",
    "id": 169,
    "letter": "S",
    "open": true,
    "startDate": "2022-06-07T00:00:00.000+02:00"
  },
  {
    "generation": "VIII",
    "id": 170,
    "letter": "T",
    "open": true,
    "startDate": "2022-06-21T00:00:00.000+02:00"
  },
  {
    "generation": "VIII",
    "id": 171,
    "letter": "U",
    "open": true,
    "startDate": "2022-07-05T00:00:00.000+02:00"
  },
  {
    "generation": "VIII",
    "id": 172,
    "letter": "W",
    "open": true,
    "startDate": "2022-07-19T00:00:00.000+02:00"
  },
  {
    "generation": "VIII",
    "id": 173,
    "letter": "Y",
    "open": true,
    "startDate": "2022-08-02T00:00:00.000+02:00"
  },
  {
    "generation": "VIII",
    "id": 174,
    "letter": "Z",
    "open": true,
    "startDate": "2022-08-16T00:00:00.000+02:00"
  }
]
